.project
AUTHORS
ChangeLog
README
files.txt
requirements.txt
setup.cfg
setup.py
.settings/org.eclipse.core.resources.prefs
dist/kt_vnfm-0.0.1.dev3.tar.gz
kt_vnfm/__init__.py
kt_vnfm/axgate_vpn.py
kt_vnfm.egg-info/PKG-INFO
kt_vnfm.egg-info/SOURCES.txt
kt_vnfm.egg-info/dependency_links.txt
kt_vnfm.egg-info/entry_points.txt
kt_vnfm.egg-info/not-zip-safe
kt_vnfm.egg-info/pbr.json
kt_vnfm.egg-info/requires.txt
kt_vnfm.egg-info/top_level.txt
kt_vnfm/connector/__init__.py
kt_vnfm/connector/vmconnector_restapi.py
kt_vnfm/connector/vmconnector_restapi_with_ns.py
kt_vnfm/connector/vmconnector_ssh.py
kt_vnfm/drivers/__init__.py
kt_vnfm/drivers/axgate_utm.py
kt_vnfm/drivers/vnf.py
kt_vnfm/drivers/vnf_states.py
kt_vnfm/utils/__init__.py
kt_vnfm/utils/auxiliary_functions.py
kt_vnfm/utils/ko_logger.py
kt_vnfm/utils/log_manager.py